docex/__init__.py
docex/cli.py
docex/context.py
docex/docCore.py
docex/docbasket.py
docex/document.py
docex/config/__init__.py
docex/config/config_manager.py
docex/config/default_config.yaml
docex/config/docex_config.py
docex/db/__init__.py
docex/db/abstract_database.py
docex/db/connection.py
docex/db/database_factory.py
docex/db/models.py
docex/db/postgres_database.py
docex/db/repository.py
docex/db/sqlite_database.py
docex/db/tenant_database_manager.py
docex/models/__init__.py
docex/models/document_metadata.py
docex/models/metadata_keys.py
docex/processors/__init__.py
docex/processors/base.py
docex/processors/csv_to_json.py
docex/processors/factory.py
docex/processors/mapper.py
docex/processors/models.py
docex/processors/pdf_invoice.py
docex/processors/pdf_to_text.py
docex/processors/word_to_text.py
docex/processors/chunking/__init__.py
docex/processors/chunking/agentic.py
docex/processors/chunking/base.py
docex/processors/chunking/document_based.py
docex/processors/chunking/factory.py
docex/processors/chunking/fixed_size.py
docex/processors/chunking/hierarchical.py
docex/processors/chunking/late.py
docex/processors/chunking/llm_based.py
docex/processors/chunking/recursive.py
docex/processors/chunking/semantic.py
docex/processors/kb/generic_kb_processor.py
docex/processors/llm/__init__.py
docex/processors/llm/base_llm_processor.py
docex/processors/llm/claude_adapter.py
docex/processors/llm/claude_service.py
docex/processors/llm/local_llm_adapter.py
docex/processors/llm/local_llm_service.py
docex/processors/llm/ollama_adapter.py
docex/processors/llm/openai_adapter.py
docex/processors/llm/openai_service.py
docex/processors/llm/prompt_manager.py
docex/processors/rag/__init__.py
docex/processors/rag/enhanced_rag_service.py
docex/processors/rag/rag_service.py
docex/processors/rag/vector_databases.py
docex/processors/rag/vector_db_monitor.py
docex/processors/vector/__init__.py
docex/processors/vector/semantic_search_service.py
docex-2.6.0.dist-info/licenses/LICENSE
docex-2.6.0.dist-info/METADATA
docex-2.6.0.dist-info/WHEEL
docex-2.6.0.dist-info/entry_points.txt
docex-2.6.0.dist-info/top_level.txt
docex-2.6.0.dist-info/RECORD
