Metadata-Version: 2.4
Name: docex
Version: 2.6.0
Summary: A robust, lightweight, and developer friendly document management and transport system for Python
Author-email: Tommy Jiang <tommySCOS@scos.ai>
License: MIT License
Classifier: Programming Language :: Python :: 3
Classifier: License :: OSI Approved :: MIT License
Classifier: Operating System :: OS Independent
Requires-Python: >=3.11
License-File: LICENSE
Requires-Dist: sqlalchemy>=2.0.0
Requires-Dist: psycopg2-binary>=2.9.0
Requires-Dist: pyyaml>=6.0.0
Requires-Dist: pytest>=7.0.0
Requires-Dist: boto3>=1.26.0
Requires-Dist: moto>=4.0.0
Requires-Dist: pydantic>=2.0.0
Requires-Dist: paramiko>=3.4.0
Requires-Dist: aiohttp>=3.9.0
Requires-Dist: python-dotenv>=1.0.0
Requires-Dist: click>=8.0.0
Requires-Dist: openai>=1.0.0
Requires-Dist: jinja2>=3.1.0
Requires-Dist: python-docx>=1.0.0
Provides-Extra: dev
Requires-Dist: pytest>=7.0.0; extra == "dev"
Requires-Dist: black>=22.0.0; extra == "dev"
Requires-Dist: isort>=5.0.0; extra == "dev"
Requires-Dist: mypy>=0.900; extra == "dev"
Provides-Extra: vector
Requires-Dist: numpy>=1.24.0; extra == "vector"
Requires-Dist: pgvector>=0.2.0; extra == "vector"
Dynamic: license-file
